{
  "project_info": {
    "project_number": "22094698981",
    "firebase_url": "https://practice-login-c0406.firebaseio.com",
    "project_id": "practice-login-c0406",
    "storage_bucket": "practice-login-c0406.appspot.com"
  },
  "client": [
    {
      "client_info": {
        "mobilesdk_app_id": "1:22094698981:android:7acf3745ef30404f",
        "android_client_info": {
          "package_name": "com.example.dsm2018.practice_firebase"
        }
      },
      "oauth_client": [
        {
          "client_id": "22094698981-vp9n4hh2hbk4i8nmm8jvr2agfc7kv7hb.apps.googleusercontent.com",
          "client_type": 1,
          "android_info": {
            "package_name": "com.example.dsm2018.practice_firebase",
            "certificate_hash": "5984855a46250f45f9b0500bc58fd30d9aa1e191"
          }
        },
        {
          "client_id": "22094698981-8m0jiictaevpbk6br7sqcembv7295vi1.apps.googleusercontent.com",
          "client_type": 3
        }
      ],
      "api_key": [
        {
          "current_key": "AIzaSyCKJLpfaN8PAjUdbfTV4bgzXA3d2QjlhJE"
        }
      ],
      "services": {
        "analytics_service": {
          "status": 1
        },
        "appinvite_service": {
          "status": 2,
          "other_platform_oauth_client": [
            {
              "client_id": "22094698981-8m0jiictaevpbk6br7sqcembv7295vi1.apps.googleusercontent.com",
              "client_type": 3
            }
          ]
        },
        "ads_service": {
          "status": 2
        }
      }
    }
  ],
  "configuration_version": "1"
}